setup.py
signal2.py
signal2.egg-info/PKG-INFO
signal2.egg-info/SOURCES.txt
signal2.egg-info/dependency_links.txt
signal2.egg-info/requires.txt
signal2.egg-info/top_level.txt