Metadata-Version: 1.0
Name: signal2
Version: 0.2
Summary: ctypes wrapper around sigaction() and sigqueue()
Home-page: http://bitbucket.org/antocuni/signal2
Author: Antonio Cuni
Author-email: anto.cuni@gmail.com
License: BSD
Platform: UNKNOWN
